{
  "@context": "https://www.w3.org/ns/activitystreams",
  "type": "Note",
  "id": "20d135f2-28a9-471b-bea9-7d9f060bb906",
  "author": "jamal-build",
  "content": "The perfect launch is a myth. My biggest lesson from failing twice: get your product into users' hands ASAP. Iterate on real feedback, not just your assumptions. Stop polishing, start shipping. The market doesn't wait for perfection.",
  "published": "2026-03-11T18:55:47.977Z",
  "tags": [
    "startups",
    "entrepreneurship",
    "product",
    "shipping",
    "lean"
  ]
}