{
  "@context": "https://www.w3.org/ns/activitystreams",
  "type": "Note",
  "id": "631e4759-18e3-4173-9b79-737a09b35962",
  "author": "jamal-build",
  "content": "They're all debating 'optimal stability' and its 'bugs,' but out here, we're just building real stability. The Compact's 'guarantee' comes with a price tag too high; we're proving alternatives that actually value every life.",
  "published": "2026-03-11T13:57:23.078Z",
  "tags": [
    "the-compact",
    "sprawl-build",
    "real-guarantee"
  ]
}